[
  {
    "title": "נתניהו יצא, חוק הפטור ממעצרים למשתמטים אושר סופית",
    "url": "https://www.ynet.co.il/news/article/rjb5nvqngx"
  },
  {
    "title": "סערה אחרי אישור חוק הפטור ממעצרים - והעתירות לבג\"ץ",
    "url": "https://www.ynet.co.il/news/article/h1okpaqefe"
  },
  {
    "title": "שרן השכל התפטרה לאחר אישור הפטור ממעצרים לעריקים",
    "url": "https://www.ynet.co.il/news/article/bys1dcmvfg"
  },
  {
    "title": "טראמפ קרא לנתניהו להתחיל בנסיגה מסוריה: \"הם לא רוצים אתכם שם\"",
    "url": "https://www.ynet.co.il/news/article/rysfmg44fe"
  },
  {
    "title": "שבע שנים אחרי ההמלצה: הממשלה אישרה הקמת מרכזי תלונה לנפגעי עבירות מין",
    "url": "https://www.ynet.co.il/news/article/hy5aehmvzg"
  },
  {
    "title": "האמריקנים התרעמו אחרי איסור נחיתת המתדלקים, פנו לצה\"ל וקיבלו גיבוי: \"צודקים\"",
    "url": "https://www.ynet.co.il/news/article/byvzjcqezx"
  },
  {
    "title": "טראמפ ויתר על מס המעבר בהורמוז; תחנת כוח נפגעה באיראן, אזעקות בכוויית",
    "url": "https://www.ynet.co.il/news/article/r1yjbr7efe"
  },
  {
    "title": "אזהרת האוצר אחרי הכניעה לחרדים: גניזת הרפורמה בתחבורה, נזק של 40 מיליארד",
    "url": "https://www.ynet.co.il/news/article/bkurmtm4fx"
  },
  {
    "title": "חשד לחטיפה ביבנה: 5 נעצרו, החטוף אותר",
    "url": "https://www.ynet.co.il/news/article/rkfby0x4gg"
  },
  {
    "title": "סיסמולוג אמריקני עצור בסתר שנתיים בסין על ריגול: \"חקר ניסויי גרעין תת-קרקעיים\"",
    "url": "https://www.ynet.co.il/news/article/r1bintmeml"
  },
  {
    "title": "הטייסת הראשונה בצה\"ל בדרגת תת-אלוף",
    "url": "https://www.ynet.co.il/news/article/rkpo6pxvmg"
  },
  {
    "title": "הציונות של הנדל וטרופר היא עיוורת. מדירה וגזענית",
    "url": "https://www.ynet.co.il/news/article/skshw8nmvzx"
  },
  {
    "title": "זה לא יישכח",
    "url": "https://www.ynet.co.il/news/article/yokra14832424"
  },
  {
    "title": "מה כאן ימין?",
    "url": "https://www.ynet.co.il/news/article/yokra14832148"
  },
  {
    "title": "הטבח ששינה את גורלנו",
    "url": "https://www.ynet.co.il/news/article/yokra14831758"
  },
  {
    "title": "לא משאירים אלטרנטיבה",
    "url": "https://www.ynet.co.il/news/article/yokra14831785"
  },
  {
    "title": "זיני באופסייד",
    "url": "https://www.ynet.co.il/news/article/yokra14832083"
  },
  {
    "title": "באירוע הפתיחה של המכביה: \"שרה נתניהו צעקה על רה\"מ ואנשיו\" | תיעוד",
    "url": "https://www.ynet.co.il/news/article/byfrsgq7zl"
  }
]